MANIFEST.in
README.rst
setup.cfg
setup.py
versioneer.py
xblock/__init__.py
xblock/_version.py
xblock/core.py
xblock/exceptions.py
xblock/field_data.py
xblock/fields.py
xblock/fragment.py
xblock/internal.py
xblock/mixins.py
xblock/plugin.py
xblock/run_script.py
xblock/runtime.py
xblock/validation.py
xblock/django/__init__.py
xblock/django/request.py
xblock/reference/__init__.py
xblock/reference/plugins.py
xblock/reference/user_service.py
xblock_openedx.egg-info/PKG-INFO
xblock_openedx.egg-info/SOURCES.txt
xblock_openedx.egg-info/dependency_links.txt
xblock_openedx.egg-info/requires.txt
xblock_openedx.egg-info/top_level.txt