Metadata-Version: 1.0
Name: xblock-openedx
Version: 0.4.1
Summary: XBlock Core Library
Home-page: https://github.com/Stanford-Online
Author: Stanford OpenEdX
Author-email: dev@lagunita.stanford.edu
License: Apache 2.0
Platform: UNKNOWN
